smod/__init__.py
smod/eco.py
unismod/__init__.py
unismod/eco.py
unismod-1.2.dist-info/METADATA
unismod-1.2.dist-info/WHEEL
unismod-1.2.dist-info/top_level.txt
unismod-1.2.dist-info/RECORD
